[{"name": "Default", "data": {"_blueamp_": {"preset": "", "bypassed": true, "ports": {"TONE": 0.5, "MASTER": 0.5, "VOLUME": 0.5, "BYPASS": 0.0}}, "CabinetIV": {"preset": "", "bypassed": true, "ports": {"model": 21.0, "gain": 0.6964285714285836}}, "_hotbox_": {"preset": "", "bypassed": true, "ports": {"BYPASS": 0.0, "VOLUME": 0.25, "GAIN": 0.7555803571428573, "BASS": 0.7154017857142859, "TREBLE": 0.5}}, "ts9sim": {"preset": "", "bypassed": false, "ports": {"fslider2_": 0.5, "fslider0_": -11.0, "fslider1_": 400.0}}, "_bottlerocket_": {"preset": "", "bypassed": true, "ports": {"BYPASS": 0.0, "VOLUME": 0.5, "GAIN": 0.7745535714285715, "BASS": 0.6919642857142858, "TREBLE": 0.5}}, "DS1": {"preset": "", "bypassed": true, "ports": {"Level": 0.5989109873771667, "Tone": 0.7816540002822876, "Dist": 0.30000001192092896}}, "_tonemachine_": {"preset": "", "bypassed": true, "ports": {"OCTAVE": 1.0, "TONE": 0.5, "VOLUME": 0.25, "SUSTAIN": 0.5625000000000001}}, "_bajatubedriver_": {"preset": "", "bypassed": true, "ports": {"TONE": 0.5, "DRIVE": 0.5747767857142858, "VOLUME": 0.3400000035762787, "BYPASS": 0.0}}, "_epic_": {"preset": "", "bypassed": true, "ports": {"TONE": 0.3984375, "BOOST": 1.0, "VOLUME": 0.5, "BYPASS": 0.0, "GAIN": 0.640625}}, "BigMuffPi": {"preset": "", "bypassed": true, "ports": {"Level": 0.1506696428571429, "Sustain": 0.26674107142857145, "Tone": 0.4252232142857143}}, "reverb": {"preset": "", "bypassed": false, "ports": {"mode": 31.0, "stereo_enh": 1.0, "bandpass_en": 1.0, "drylevel": -4.0, "combs_en": 1.0, "wetlevel": -17.767857142857153, "allps_en": 1.0, "decay": 2800.0}}}}, {"name": "MedHot", "data": {"_blueamp_": {"preset": "", "bypassed": true, "ports": {"TONE": 0.5, "MASTER": 0.5, "VOLUME": 0.5, "BYPASS": 0.0}}, "CabinetIV": {"preset": "", "bypassed": false, "ports": {"model": 21.0, "gain": 0.6964285714285836}}, "_hotbox_": {"preset": "", "bypassed": false, "ports": {"BYPASS": 0.0, "VOLUME": 0.1339285714285714, "GAIN": 0.7555803571428573, "BASS": 0.7154017857142859, "TREBLE": 0.5}}, "ts9sim": {"preset": "", "bypassed": true, "ports": {"fslider2_": 0.5, "fslider0_": -9.875, "fslider1_": 400.0}}, "_bottlerocket_": {"preset": "", "bypassed": true, "ports": {"BYPASS": 0.0, "VOLUME": 0.5, "GAIN": 0.7745535714285715, "BASS": 0.6919642857142858, "TREBLE": 0.5}}, "DS1": {"preset": "", "bypassed": true, "ports": {"Level": 0.5989109873771667, "Tone": 0.7816540002822876, "Dist": 0.30000001192092896}}, "_tonemachine_": {"preset": "", "bypassed": true, "ports": {"OCTAVE": 1.0, "TONE": 0.5, "VOLUME": 0.25, "SUSTAIN": 0.5625000000000001}}, "_bajatubedriver_": {"preset": "", "bypassed": true, "ports": {"TONE": 0.5, "DRIVE": 0.5747767857142858, "VOLUME": 0.3400000035762787, "BYPASS": 0.0}}, "_epic_": {"preset": "", "bypassed": true, "ports": {"TONE": 0.3984375, "BOOST": 1.0, "VOLUME": 0.5, "BYPASS": 0.0, "GAIN": 0.640625}}, "BigMuffPi": {"preset": "", "bypassed": true, "ports": {"Level": 0.1506696428571429, "Sustain": 0.26674107142857145, "Tone": 0.4252232142857143}}, "reverb": {"preset": "", "bypassed": false, "ports": {"mode": 31.0, "stereo_enh": 1.0, "bandpass_en": 1.0, "drylevel": -4.0, "combs_en": 1.0, "wetlevel": -17.767857142857153, "allps_en": 1.0, "decay": 2800.0}}}}, {"name": "Slight", "data": {"_blueamp_": {"preset": "", "bypassed": true, "ports": {"TONE": 0.5, "MASTER": 0.5, "VOLUME": 0.5, "BYPASS": 0.0}}, "CabinetIV": {"preset": "", "bypassed": false, "ports": {"model": 21.0, "gain": 0.6964285714285836}}, "_hotbox_": {"preset": "", "bypassed": false, "ports": {"BYPASS": 0.0, "VOLUME": 0.16741071428571425, "GAIN": 0.4341517857142861, "BASS": 0.7154017857142859, "TREBLE": 0.5}}, "ts9sim": {"preset": "", "bypassed": true, "ports": {"fslider2_": 0.5, "fslider0_": -9.875, "fslider1_": 400.0}}, "_bottlerocket_": {"preset": "", "bypassed": true, "ports": {"BYPASS": 0.0, "VOLUME": 0.5, "GAIN": 0.7745535714285715, "BASS": 0.6919642857142858, "TREBLE": 0.5}}, "DS1": {"preset": "", "bypassed": true, "ports": {"Level": 0.5989109873771667, "Tone": 0.7816540002822876, "Dist": 0.30000001192092896}}, "_tonemachine_": {"preset": "", "bypassed": true, "ports": {"OCTAVE": 1.0, "TONE": 0.5, "VOLUME": 0.25, "SUSTAIN": 0.5625000000000001}}, "_bajatubedriver_": {"preset": "", "bypassed": true, "ports": {"TONE": 0.5, "DRIVE": 0.5747767857142858, "VOLUME": 0.3400000035762787, "BYPASS": 0.0}}, "_epic_": {"preset": "", "bypassed": true, "ports": {"TONE": 0.3984375, "BOOST": 1.0, "VOLUME": 0.5, "BYPASS": 0.0, "GAIN": 0.640625}}, "BigMuffPi": {"preset": "", "bypassed": true, "ports": {"Level": 0.1506696428571429, "Sustain": 0.26674107142857145, "Tone": 0.4252232142857143}}, "reverb": {"preset": "", "bypassed": false, "ports": {"mode": 31.0, "stereo_enh": 1.0, "bandpass_en": 1.0, "drylevel": -4.0, "combs_en": 1.0, "wetlevel": -17.767857142857153, "allps_en": 1.0, "decay": 2800.0}}}}, {"name": "Fuzz", "data": {"_blueamp_": {"preset": "", "bypassed": true, "ports": {"TONE": 0.5, "MASTER": 0.5, "VOLUME": 0.5, "BYPASS": 0.0}}, "CabinetIV": {"preset": "", "bypassed": false, "ports": {"model": 21.0, "gain": 0.6964285714285836}}, "_hotbox_": {"preset": "", "bypassed": true, "ports": {"BYPASS": 0.0, "VOLUME": 0.25, "GAIN": 0.7555803571428573, "BASS": 0.7154017857142859, "TREBLE": 0.5}}, "ts9sim": {"preset": "", "bypassed": true, "ports": {"fslider2_": 0.5, "fslider0_": -11.0, "fslider1_": 400.0}}, "_bottlerocket_": {"preset": "", "bypassed": true, "ports": {"BYPASS": 0.0, "VOLUME": 0.5, "GAIN": 0.7745535714285715, "BASS": 0.6919642857142858, "TREBLE": 0.5}}, "DS1": {"preset": "", "bypassed": true, "ports": {"Level": 0.3513390060236868, "Tone": 0.6019908209891173, "Dist": 0.30000001192092896}}, "_tonemachine_": {"preset": "", "bypassed": true, "ports": {"OCTAVE": 1.0, "TONE": 0.5, "VOLUME": 0.25, "SUSTAIN": 0.5625000000000001}}, "_bajatubedriver_": {"preset": "", "bypassed": true, "ports": {"TONE": 0.5, "DRIVE": 0.5747767857142858, "VOLUME": 0.3400000035762787, "BYPASS": 0.0}}, "_epic_": {"preset": "", "bypassed": true, "ports": {"TONE": 0.3984375, "BOOST": 1.0, "VOLUME": 0.5, "BYPASS": 0.0, "GAIN": 0.640625}}, "BigMuffPi": {"preset": "", "bypassed": false, "ports": {"Level": 0.11718749999999999, "Sustain": 0.26674107142857145, "Tone": 0.4252232142857143}}, "reverb": {"preset": "", "bypassed": false, "ports": {"mode": 31.0, "stereo_enh": 1.0, "bandpass_en": 1.0, "drylevel": -4.0, "combs_en": 1.0, "wetlevel": -17.767857142857153, "allps_en": 1.0, "decay": 2800.0}}}}]